cherryontop/__init__.py
cherryontop/cache.py
cherryontop/decos.py
cherryontop/discover.py
cherryontop/dispatcher.py
cherryontop/errors.py
cherryontop/requests.py
cherryontop/spinup.py
cherryontop/utils.py
cherryontop-0.4.4.dist-info/DESCRIPTION.rst
cherryontop-0.4.4.dist-info/METADATA
cherryontop-0.4.4.dist-info/RECORD
cherryontop-0.4.4.dist-info/WHEEL
cherryontop-0.4.4.dist-info/metadata.json
cherryontop-0.4.4.dist-info/top_level.txt
